litreview/__init__.py
litreview/config.yaml
litreview/defaultlayout.md
litreview/main.py
litreview/__pycache__/__init__.cpython-38.pyc
litreview/src/__init__.py
litreview/src/argparser.py
litreview/src/extractor.py
litreview/src/get_post.py
litreview/src/logger.py
litreview/src/shell_utils.py
litreview/src/string_evaluation.py
litreview/src/utils.py
litreview/src/__pycache__/__init__.cpython-38.pyc
litreview/src/__pycache__/argparser.cpython-38.pyc
litreview/src/__pycache__/extractor.cpython-38.pyc
litreview/src/__pycache__/get_post.cpython-38.pyc
litreview/src/__pycache__/shell_utils.cpython-38.pyc
litreview/src/__pycache__/utils.cpython-38.pyc
lit_review-0.0.9.dist-info/LICENSE
lit_review-0.0.9.dist-info/METADATA
lit_review-0.0.9.dist-info/WHEEL
lit_review-0.0.9.dist-info/entry_points.txt
lit_review-0.0.9.dist-info/top_level.txt
lit_review-0.0.9.dist-info/RECORD
