Metadata-Version: 2.1
Name: lit-review
Version: 0.0.9
Summary: Automate creation of reports and working directories for literature reviews
Home-page: https://github.com/Velythyl/litreview
Author: Charlie Gauthier
Author-email: charlie.gauthier@umontreal.ca
License: MIT
Platform: UNKNOWN
License-File: LICENSE
Requires-Dist: pyyaml
Requires-Dist: beautifulsoup4
Requires-Dist: validators
Requires-Dist: six
Requires-Dist: soupsieve
Requires-Dist: twine
